niwrap/__init__.py
niwrap-0.8.3.dist-info/WHEEL
niwrap-0.8.3.dist-info/METADATA
niwrap-0.8.3.dist-info/RECORD
