Metadata-Version: 2.4
Name: niwrap
Version: 0.8.3
Summary: Neuroimaging wrappers.
Author: CMI DAIR
License-Expression: MIT
Requires-Dist: styxdocker
Requires-Dist: styxsingularity
Requires-Dist: styxgraph
Requires-Dist: niwrap-afni
Requires-Dist: niwrap-ants
Requires-Dist: niwrap-c3d
Requires-Dist: niwrap-dcm2niix
Requires-Dist: niwrap-fastsurfer
Requires-Dist: niwrap-freesurfer
Requires-Dist: niwrap-fsl
Requires-Dist: niwrap-greedy
Requires-Dist: niwrap-mrtrix
Requires-Dist: niwrap-mrtrix3tissue
Requires-Dist: niwrap-niftyreg
Requires-Dist: niwrap-workbench
Requires-Python: >=3.10
